drf_extra_fields/__init__.py
drf_extra_fields/compat.py
drf_extra_fields/fields.py
drf_extra_fields/geo_fields.py
drf_extra_fields/relations.py
drf_extra_fields/runtests/__init__.py
drf_extra_fields/runtests/settings.py
drf_extra_fields-3.7.0.dist-info/LICENSE
drf_extra_fields-3.7.0.dist-info/METADATA
drf_extra_fields-3.7.0.dist-info/WHEEL
drf_extra_fields-3.7.0.dist-info/top_level.txt
drf_extra_fields-3.7.0.dist-info/RECORD
