Metadata-Version: 2.1
Name: drf-extra-fields
Version: 3.7.0
Summary: Additional fields for Django Rest Framework.
Home-page: https://github.com/Hipo/drf-extra-fields
Author: hipo
Author-email: pypi@hipolabs.com
License: Apache-2.0
Classifier: Environment :: Web Environment
Classifier: Framework :: Django
Classifier: Intended Audience :: Developers
Classifier: Operating System :: OS Independent
Classifier: License :: OSI Approved :: BSD License
Classifier: Programming Language :: Python
Classifier: Programming Language :: Python :: 3
Classifier: Programming Language :: Python :: 3.7
Classifier: Programming Language :: Python :: 3.8
Classifier: Programming Language :: Python :: 3.9
Classifier: Programming Language :: Python :: 3.10
Classifier: Programming Language :: Python :: 3.11
Classifier: Topic :: Internet :: WWW/HTTP
Classifier: Topic :: Internet :: WWW/HTTP :: Dynamic Content
Requires-Python: >=3.7
Provides-Extra: Base64ImageField
License-File: LICENSE
